setup.py
uidesign/__init__.py
uidesign/uidesign.py
uidesign.egg-info/PKG-INFO
uidesign.egg-info/SOURCES.txt
uidesign.egg-info/dependency_links.txt
uidesign.egg-info/top_level.txt