Metadata-Version: 2.1
Name: uidesign
Version: 0.0.1
Summary: Create art in the terminal
Author: cdg
